spike_py_utils/__init__.py
spike_py_utils/dataflow.py
spike_py_utils-0.1.3.dist-info/LICENSE
spike_py_utils-0.1.3.dist-info/WHEEL
spike_py_utils-0.1.3.dist-info/METADATA
spike_py_utils-0.1.3.dist-info/RECORD
