Metadata-Version: 2.1
Name: spike-py-utils
Version: 0.1.3
Summary: Assortment of datascience and data engineering utilities
License: MIT
Author: cd
Author-email: cdagnino@gmail.com
Requires-Python: >=3.8,<4.0
Classifier: License :: OSI Approved :: MIT License
Classifier: Programming Language :: Python :: 3
Classifier: Programming Language :: Python :: 3.8
Classifier: Programming Language :: Python :: 3.9
Requires-Dist: numpy (>=1.18,<2.0)
